{
  "id": "393bfbe9-35b2-4aab-893f-823d8498549f",
  "prevId": "00000000-0000-0000-0000-000000000000",
  "version": "7",
  "dialect": "postgresql",
  "tables": {
    "public.download_grants": {
      "name": "download_grants",
      "schema": "",
      "columns": {
        "id": {
          "name": "id",
          "type": "varchar(24)",
          "primaryKey": true,
          "notNull": true
        },
        "room_id": {
          "name": "room_id",
          "type": "varchar(24)",
          "primaryKey": false,
          "notNull": true
        },
        "track_id": {
          "name": "track_id",
          "type": "varchar(24)",
          "primaryKey": false,
          "notNull": false
        },
        "participant_role": {
          "name": "participant_role",
          "type": "participant_role",
          "typeSchema": "public",
          "primaryKey": false,
          "notNull": true
        },
        "token": {
          "name": "token",
          "type": "varchar(64)",
          "primaryKey": false,
          "notNull": true
        },
        "downloaded": {
          "name": "downloaded",
          "type": "boolean",
          "primaryKey": false,
          "notNull": true,
          "default": false
        },
        "downloaded_at": {
          "name": "downloaded_at",
          "type": "timestamp with time zone",
          "primaryKey": false,
          "notNull": false
        },
        "download_count": {
          "name": "download_count",
          "type": "integer",
          "primaryKey": false,
          "notNull": true,
          "default": 0
        },
        "max_downloads": {
          "name": "max_downloads",
          "type": "integer",
          "primaryKey": false,
          "notNull": true,
          "default": 1
        },
        "expires_at": {
          "name": "expires_at",
          "type": "timestamp with time zone",
          "primaryKey": false,
          "notNull": true
        },
        "created_at": {
          "name": "created_at",
          "type": "timestamp with time zone",
          "primaryKey": false,
          "notNull": true,
          "default": "now()"
        }
      },
      "indexes": {
        "download_grants_room_id_idx": {
          "name": "download_grants_room_id_idx",
          "columns": [
            {
              "expression": "room_id",
              "isExpression": false,
              "asc": true,
              "nulls": "last"
            }
          ],
          "isUnique": false,
          "concurrently": false,
          "method": "btree",
          "with": {}
        }
      },
      "foreignKeys": {
        "download_grants_room_id_rooms_id_fk": {
          "name": "download_grants_room_id_rooms_id_fk",
          "tableFrom": "download_grants",
          "tableTo": "rooms",
          "columnsFrom": [
            "room_id"
          ],
          "columnsTo": [
            "id"
          ],
          "onDelete": "no action",
          "onUpdate": "no action"
        },
        "download_grants_track_id_tracks_id_fk": {
          "name": "download_grants_track_id_tracks_id_fk",
          "tableFrom": "download_grants",
          "tableTo": "tracks",
          "columnsFrom": [
            "track_id"
          ],
          "columnsTo": [
            "id"
          ],
          "onDelete": "no action",
          "onUpdate": "no action"
        }
      },
      "compositePrimaryKeys": {},
      "uniqueConstraints": {
        "download_grants_token_unique": {
          "name": "download_grants_token_unique",
          "nullsNotDistinct": false,
          "columns": [
            "token"
          ]
        }
      },
      "policies": {},
      "checkConstraints": {},
      "isRLSEnabled": false
    },
    "public.rooms": {
      "name": "rooms",
      "schema": "",
      "columns": {
        "id": {
          "name": "id",
          "type": "varchar(24)",
          "primaryKey": true,
          "notNull": true
        },
        "status": {
          "name": "status",
          "type": "room_status",
          "typeSchema": "public",
          "primaryKey": false,
          "notNull": true,
          "default": "'created'"
        },
        "creator_secret_hash": {
          "name": "creator_secret_hash",
          "type": "varchar(64)",
          "primaryKey": false,
          "notNull": true
        },
        "joiner_secret_hash": {
          "name": "joiner_secret_hash",
          "type": "varchar(64)",
          "primaryKey": false,
          "notNull": false
        },
        "invite_token": {
          "name": "invite_token",
          "type": "varchar(64)",
          "primaryKey": false,
          "notNull": true
        },
        "invite_used": {
          "name": "invite_used",
          "type": "boolean",
          "primaryKey": false,
          "notNull": true,
          "default": false
        },
        "created_at": {
          "name": "created_at",
          "type": "timestamp with time zone",
          "primaryKey": false,
          "notNull": true,
          "default": "now()"
        },
        "completed_at": {
          "name": "completed_at",
          "type": "timestamp with time zone",
          "primaryKey": false,
          "notNull": false
        },
        "expires_at": {
          "name": "expires_at",
          "type": "timestamp with time zone",
          "primaryKey": false,
          "notNull": false
        },
        "creator_approved_at": {
          "name": "creator_approved_at",
          "type": "timestamp with time zone",
          "primaryKey": false,
          "notNull": false
        },
        "joiner_approved_at": {
          "name": "joiner_approved_at",
          "type": "timestamp with time zone",
          "primaryKey": false,
          "notNull": false
        },
        "joined_at": {
          "name": "joined_at",
          "type": "timestamp with time zone",
          "primaryKey": false,
          "notNull": false
        },
        "cancellation_reason": {
          "name": "cancellation_reason",
          "type": "text",
          "primaryKey": false,
          "notNull": false
        },
        "cancelled_by": {
          "name": "cancelled_by",
          "type": "participant_role",
          "typeSchema": "public",
          "primaryKey": false,
          "notNull": false
        },
        "cancelled_at": {
          "name": "cancelled_at",
          "type": "timestamp with time zone",
          "primaryKey": false,
          "notNull": false
        }
      },
      "indexes": {
        "rooms_status_idx": {
          "name": "rooms_status_idx",
          "columns": [
            {
              "expression": "status",
              "isExpression": false,
              "asc": true,
              "nulls": "last"
            }
          ],
          "isUnique": false,
          "concurrently": false,
          "method": "btree",
          "with": {}
        },
        "rooms_expires_at_idx": {
          "name": "rooms_expires_at_idx",
          "columns": [
            {
              "expression": "expires_at",
              "isExpression": false,
              "asc": true,
              "nulls": "last"
            }
          ],
          "isUnique": false,
          "concurrently": false,
          "method": "btree",
          "with": {}
        }
      },
      "foreignKeys": {},
      "compositePrimaryKeys": {},
      "uniqueConstraints": {
        "rooms_invite_token_unique": {
          "name": "rooms_invite_token_unique",
          "nullsNotDistinct": false,
          "columns": [
            "invite_token"
          ]
        }
      },
      "policies": {},
      "checkConstraints": {},
      "isRLSEnabled": false
    },
    "public.tracks": {
      "name": "tracks",
      "schema": "",
      "columns": {
        "id": {
          "name": "id",
          "type": "varchar(24)",
          "primaryKey": true,
          "notNull": true
        },
        "room_id": {
          "name": "room_id",
          "type": "varchar(24)",
          "primaryKey": false,
          "notNull": true
        },
        "role": {
          "name": "role",
          "type": "participant_role",
          "typeSchema": "public",
          "primaryKey": false,
          "notNull": true
        },
        "original_filename": {
          "name": "original_filename",
          "type": "text",
          "primaryKey": false,
          "notNull": true
        },
        "stored_filename": {
          "name": "stored_filename",
          "type": "varchar(64)",
          "primaryKey": false,
          "notNull": true
        },
        "file_size_bytes": {
          "name": "file_size_bytes",
          "type": "integer",
          "primaryKey": false,
          "notNull": true
        },
        "mime_type": {
          "name": "mime_type",
          "type": "varchar(128)",
          "primaryKey": false,
          "notNull": true
        },
        "duration_seconds": {
          "name": "duration_seconds",
          "type": "integer",
          "primaryKey": false,
          "notNull": false
        },
        "bitrate_kbps": {
          "name": "bitrate_kbps",
          "type": "integer",
          "primaryKey": false,
          "notNull": false
        },
        "sample_rate_hz": {
          "name": "sample_rate_hz",
          "type": "integer",
          "primaryKey": false,
          "notNull": false
        },
        "codec": {
          "name": "codec",
          "type": "varchar(32)",
          "primaryKey": false,
          "notNull": false
        },
        "bpm": {
          "name": "bpm",
          "type": "integer",
          "primaryKey": false,
          "notNull": false
        },
        "bpm_confidence": {
          "name": "bpm_confidence",
          "type": "integer",
          "primaryKey": false,
          "notNull": false
        },
        "spectrogram_path": {
          "name": "spectrogram_path",
          "type": "text",
          "primaryKey": false,
          "notNull": false
        },
        "waveform_json_path": {
          "name": "waveform_json_path",
          "type": "text",
          "primaryKey": false,
          "notNull": false
        },
        "snippet_path": {
          "name": "snippet_path",
          "type": "text",
          "primaryKey": false,
          "notNull": false
        },
        "encrypted_dek": {
          "name": "encrypted_dek",
          "type": "text",
          "primaryKey": false,
          "notNull": false
        },
        "encryption_iv": {
          "name": "encryption_iv",
          "type": "text",
          "primaryKey": false,
          "notNull": false
        },
        "processing_status": {
          "name": "processing_status",
          "type": "processing_status",
          "typeSchema": "public",
          "primaryKey": false,
          "notNull": true,
          "default": "'pending'"
        },
        "processing_error": {
          "name": "processing_error",
          "type": "text",
          "primaryKey": false,
          "notNull": false
        },
        "uploaded_at": {
          "name": "uploaded_at",
          "type": "timestamp with time zone",
          "primaryKey": false,
          "notNull": true,
          "default": "now()"
        },
        "processed_at": {
          "name": "processed_at",
          "type": "timestamp with time zone",
          "primaryKey": false,
          "notNull": false
        }
      },
      "indexes": {
        "tracks_room_id_idx": {
          "name": "tracks_room_id_idx",
          "columns": [
            {
              "expression": "room_id",
              "isExpression": false,
              "asc": true,
              "nulls": "last"
            }
          ],
          "isUnique": false,
          "concurrently": false,
          "method": "btree",
          "with": {}
        }
      },
      "foreignKeys": {
        "tracks_room_id_rooms_id_fk": {
          "name": "tracks_room_id_rooms_id_fk",
          "tableFrom": "tracks",
          "tableTo": "rooms",
          "columnsFrom": [
            "room_id"
          ],
          "columnsTo": [
            "id"
          ],
          "onDelete": "no action",
          "onUpdate": "no action"
        }
      },
      "compositePrimaryKeys": {},
      "uniqueConstraints": {},
      "policies": {},
      "checkConstraints": {},
      "isRLSEnabled": false
    }
  },
  "enums": {
    "public.participant_role": {
      "name": "participant_role",
      "schema": "public",
      "values": [
        "creator",
        "joiner"
      ]
    },
    "public.processing_status": {
      "name": "processing_status",
      "schema": "public",
      "values": [
        "pending",
        "processing",
        "completed",
        "failed"
      ]
    },
    "public.room_status": {
      "name": "room_status",
      "schema": "public",
      "values": [
        "created",
        "waiting_for_peer",
        "processing",
        "ready_for_review",
        "a_approved",
        "b_approved",
        "completed",
        "cancelled",
        "disputed",
        "expired"
      ]
    }
  },
  "schemas": {},
  "sequences": {},
  "roles": {},
  "policies": {},
  "views": {},
  "_meta": {
    "columns": {},
    "schemas": {},
    "tables": {}
  }
}